README.txt
buildout.cfg
setup.cfg
setup.py
collective/__init__.py
collective.js.jquery.egg-info/PKG-INFO
collective.js.jquery.egg-info/SOURCES.txt
collective.js.jquery.egg-info/dependency_links.txt
collective.js.jquery.egg-info/entry_points.txt
collective.js.jquery.egg-info/namespace_packages.txt
collective.js.jquery.egg-info/not-zip-safe
collective.js.jquery.egg-info/requires.txt
collective.js.jquery.egg-info/top_level.txt
collective/js/__init__.py
collective/js/jquery/__init__.py
collective/js/jquery/configure.zcml
collective/js/jquery/jquery-1.3.2.min.js
collective/js/jquery/profiles/default/jsregistry.xml
collective/js/jquery/profiles/default/metadata.xml
docs/GPL-LICENSE.txt
docs/HISTORY.txt
docs/MIT-LICENSE.txt