Metadata-Version: 1.0
Name: collective.js.jquery
Version: 1.3.2.1dev-r84292
Summary: A packaging of the jQuery library for Zope
Home-page: UNKNOWN
Author: UNKNOWN
Author-email: UNKNOWN
License: MIT
Platform: UNKNOWN
Classifier: Programming Language :: Python
Classifier: Topic :: Software Development :: Libraries :: Python Modules
